<?xml version="1.0" encoding="utf-8"?>
<Sentences>
  <Sentence ID="ps76:1">
    <Trees>
      <Tree>
        <Node Cat="S" Head="0" Start="0" End="8" nodeId="190760010010090" Length="9">
          <Node Id="1.1" Cat="CL" Start="0" End="2" Rule="PP2CL" Head="0" Language="H" nodeId="190760010010032" Length="3">
            <Node Id="1.2" Cat="PP" Start="0" End="2" Rule="Pp2PP" Head="0" Language="H" nodeId="190760010010031" Length="3">
              <Node Id="1.3" Cat="pp" Start="0" End="2" Rule="PrepNp" Head="1" Language="H" nodeId="190760010010030" Length="3">
                <Node Id="1.4" Cat="pp" Start="0" End="0" Rule="P2PP" Head="0" Language="H" nodeId="190760010010011" Length="1">
                  <Node Id="1.5" Cat="prep" Start="0" End="0" Lemma="L:" UnicodeLemma="לְ" English="for" Analysis="Pp" morphId="190760010011" StrongNumberX="3807a" Language="H" Unicode="לַ‎" nodeId="190760010010010" Length="1">LA</Node>
                </Node>
                <Node Id="1.6" Cat="np" Start="1" End="2" Rule="DetNP" Head="1" Language="H" nodeId="190760010020020" Length="2">
                  <Node Id="1.7" Cat="art" Start="1" End="1" Lemma="HA" UnicodeLemma="הַ" English="the" Analysis="Pa" morphId="190760010012" StrongNumberX="1886a" Language="H" Unicode="‎" nodeId="190760010020010" Length="1">_</Node>
                  <Node Id="1.8" Cat="np" Start="2" End="2" Rule="Vp2Np" Head="0" Language="H" nodeId="190760010030012" Length="1">
                    <Node Id="1.9" Cat="vp" Start="2" End="2" Rule="V2VP" Head="0" Language="H" nodeId="190760010030011" Length="1">
                      <Node Id="1.10" Cat="verb" Start="2" End="2" Lemma="NCX" UnicodeLemma="נצח" English="one directing" Analysis="vpPmsa" morphId="190760010013" StrongNumberX="5329" Language="H" Unicode="מְנַצֵּ֥חַ‎" nodeId="190760010030010" Length="1">M:NAC."71XA</Node>
                    </Node>
                  </Node>
                </Node>
              </Node>
            </Node>
          </Node>
          <Node Id="9.1" Cat="CL" Start="3" End="4" Rule="PP2CL" Head="0" Language="H" nodeId="190760010040022" Length="2">
            <Node Id="9.2" Cat="PP" Start="3" End="4" Rule="Pp2PP" Head="0" Language="H" nodeId="190760010040021" Length="2">
              <Node Id="9.3" Cat="pp" Start="3" End="4" Rule="PrepNp" Head="1" Language="H" nodeId="190760010040020" Length="2">
                <Node Id="9.4" Cat="pp" Start="3" End="3" Rule="P2PP" Head="0" Language="H" nodeId="190760010040011" Length="1">
                  <Node Id="9.5" Cat="prep" Start="3" End="3" Lemma="B.:" UnicodeLemma="בְּ" English="with" Analysis="Pp" morphId="190760010021" StrongNumberX="0871a" Language="H" Unicode="בִּ‎" nodeId="190760010040010" Length="1">B.I</Node>
                </Node>
                <Node Id="9.6" Cat="np" Start="4" End="4" Rule="N2NP" Head="0" Language="H" nodeId="190760010050011" Length="1">
                  <Node Id="9.7" Cat="noun" Start="4" End="4" Lemma="N:GIYNFH" UnicodeLemma="נְגִינָה" English="stringed instruments" Analysis="ncfpa" morphId="190760010022" StrongNumberX="5058" Language="H" Unicode="נְגִינֹ֑ת‎" nodeId="190760010050010" Length="1">N:GIYNO92T</Node>
                </Node>
              </Node>
            </Node>
          </Node>
          <Node Id="14.1" Cat="CL" Start="5" End="7" Rule="S-P" Head="1" Language="H" nodeId="190760010060030" Length="3">
            <Node Id="14.2" Cat="S" Start="5" End="5" Rule="Np2S" Head="0" Language="H" nodeId="190760010060012" Length="1">
              <Node Id="14.3" Cat="np" Start="5" End="5" Rule="N2NP" Head="0" Language="H" nodeId="190760010060011" Length="1">
                <Node Id="14.4" Cat="noun" Start="5" End="5" Lemma="MIZ:MOWR" UnicodeLemma="מִזְמוֹר" English="psalm" Analysis="ncmsa" morphId="190760010031" StrongNumberX="4210" Language="H" Unicode="מִזְמ֖וֹר‎" nodeId="190760010060010" Length="1">MIZ:MO73WR</Node>
              </Node>
            </Node>
            <Node Id="14.5" Cat="P" Start="6" End="7" Rule="Pp2P" Head="0" Language="H" nodeId="190760010070021" Length="2">
              <Node Id="14.6" Cat="pp" Start="6" End="7" Rule="PrepNp" Head="1" Language="H" nodeId="190760010070020" Length="2">
                <Node Id="14.7" Cat="pp" Start="6" End="6" Rule="P2PP" Head="0" Language="H" nodeId="190760010070011" Length="1">
                  <Node Id="14.8" Cat="prep" Start="6" End="6" Lemma="L:" UnicodeLemma="לְ" English="of" Analysis="Pp" morphId="190760010041" StrongNumberX="3807a" Language="H" Unicode="לְ‎" nodeId="190760010070010" Length="1">L:</Node>
                </Node>
                <Node Id="14.9" Cat="np" Start="7" End="7" Rule="N2NP" Head="0" Language="H" nodeId="190760010080011" Length="1">
                  <Node Id="14.10" Cat="noun" Start="7" End="7" Lemma=")FSFP" UnicodeLemma="אָסָף" English="Asaph" Analysis="np" morphId="190760010042" StrongNumberX="0623" Language="H" Unicode="אָסָ֣ף‎" nodeId="190760010080010" Length="1">)FSF74P</Node>
                </Node>
              </Node>
            </Node>
          </Node>
          <Node Id="21.1" Cat="CL" Start="8" End="8" Rule="P2CL" Head="0" Language="H" nodeId="190760010090013" Length="1">
            <Node Id="21.2" Cat="P" Start="8" End="8" Rule="Np2P" Head="0" Language="H" nodeId="190760010090012" Length="1">
              <Node Id="21.3" Cat="np" Start="8" End="8" Rule="N2NP" Head="0" Language="H" nodeId="190760010090011" Length="1">
                <Node Id="21.4" Cat="noun" Start="8" End="8" Lemma="$IYR" UnicodeLemma="שִׁיר" English="song" Analysis="ncmsa" morphId="190760010051" StrongNumberX="7892" Language="H" Unicode="׃‎שִֽׁיר‎" nodeId="190760010090010" Length="1">$I75YR00</Node>
              </Node>
            </Node>
          </Node>
        </Node>
      </Tree>
    </Trees>
  </Sentence>
  <Sentence ID="ps76:2">
    <Trees>
      <Tree>
        <Node Cat="S" Head="0" Start="0" End="8" nodeId="190760020010090" Length="9">
          <Node Id="2.1" Cat="CL" Start="0" End="3" Rule="V-PP-S" Head="0" Language="H" nodeId="190760020010040" Length="4">
            <Node Id="2.2" Cat="V" Start="0" End="0" Rule="Vp2V" Head="0" Language="H" nodeId="190760020010012" Length="1">
              <Node Id="2.3" Cat="vp" Start="0" End="0" Rule="V2VP" Head="0" Language="H" nodeId="190760020010011" Length="1">
                <Node Id="2.4" Cat="verb" Start="0" End="0" Lemma="YD(" UnicodeLemma="ידע" English="one being known" Analysis="vnPmsa" morphId="190760020011" StrongNumberX="3045" Language="H" Unicode="נוֹדָ֣ע‎" nodeId="190760020010010" Length="1">NOWDF74(</Node>
              </Node>
            </Node>
            <Node Id="2.5" Cat="PP" Start="1" End="2" Rule="Pp2PP" Head="0" Language="H" nodeId="190760020020021" Length="2">
              <Node Id="2.6" Cat="pp" Start="1" End="2" Rule="PrepNp" Head="1" Language="H" nodeId="190760020020020" Length="2">
                <Node Id="2.7" Cat="pp" Start="1" End="1" Rule="P2PP" Head="0" Language="H" nodeId="190760020020011" Length="1">
                  <Node Id="2.8" Cat="prep" Start="1" End="1" Lemma="B.:" UnicodeLemma="בְּ" English="in" Analysis="Pp" morphId="190760020021" StrongNumberX="0871a" Language="H" Unicode="בִּֽ‎" nodeId="190760020020010" Length="1">B.I75</Node>
                </Node>
                <Node Id="2.9" Cat="np" Start="2" End="2" Rule="N2NP" Head="0" Language="H" nodeId="190760020030011" Length="1">
                  <Node Id="2.10" Cat="noun" Start="2" End="2" Lemma="Y:HW.DFH" UnicodeLemma="יְהוּדָה" English="Judah" Analysis="np" morphId="190760020022" StrongNumberX="3063" Language="H" Unicode="יהוּדָ֣ה‎" nodeId="190760020030010" Length="1">YHW.DF74H</Node>
                </Node>
              </Node>
            </Node>
            <Node Id="2.11" Cat="S" Start="3" End="3" Rule="Np2S" Head="0" Language="H" nodeId="190760020040012" Length="1">
              <Node Id="2.12" Cat="np" Start="3" End="3" Rule="N2NP" Head="0" Language="H" nodeId="190760020040011" Length="1">
                <Node Id="2.13" Cat="noun" Start="3" End="3" Lemma="):ELOHIYM" UnicodeLemma="אֱלֹהִים" English="God" Analysis="ncmpa" morphId="190760020031" StrongNumberX="0430" Language="H" Unicode="אֱלֹהִ֑ים‎" nodeId="190760020040010" Length="1">):ELOHI92YM</Node>
              </Node>
            </Node>
          </Node>
          <Node Id="9.1" Cat="CL" Start="4" End="8" Rule="PP-P-S" Head="1" Language="H" nodeId="190760020050050" Length="5">
            <Node Id="9.2" Cat="PP" Start="4" End="5" Rule="Pp2PP" Head="0" Language="H" nodeId="190760020050021" Length="2">
              <Node Id="9.3" Cat="pp" Start="4" End="5" Rule="PrepNp" Head="1" Language="H" nodeId="190760020050020" Length="2">
                <Node Id="9.4" Cat="pp" Start="4" End="4" Rule="P2PP" Head="0" Language="H" nodeId="190760020050011" Length="1">
                  <Node Id="9.5" Cat="prep" Start="4" End="4" Lemma="B.:" UnicodeLemma="בְּ" English="in" Analysis="Pp" morphId="190760020041" StrongNumberX="0871a" Language="H" Unicode="בְּ֝‎" nodeId="190760020050010" Length="1">11B.:</Node>
                </Node>
                <Node Id="9.6" Cat="np" Start="5" End="5" Rule="N2NP" Head="0" Language="H" nodeId="190760020060011" Length="1">
                  <Node Id="9.7" Cat="noun" Start="5" End="5" Lemma="YI&amp;:RF)&quot;L" UnicodeLemma="יִשְׂרָאֵל" English="Israel" Analysis="np" morphId="190760020042" StrongNumberX="3478" Language="H" Unicode="יִשְׂרָאֵ֗ל‎" nodeId="190760020060010" Length="1">YI&amp;:RF)"81L</Node>
                </Node>
              </Node>
            </Node>
            <Node Id="9.8" Cat="P" Start="6" End="6" Rule="Adjp2P" Head="0" Language="H" nodeId="190760020070012" Length="1">
              <Node Id="9.9" Cat="adjp" Start="6" End="6" Rule="Adj2Adjp" Head="0" Language="H" nodeId="190760020070011" Length="1">
                <Node Id="9.10" Cat="adj" Start="6" End="6" Lemma="G.FDOWL" UnicodeLemma="גָּדוֹל" English="great" Analysis="amsa" morphId="190760020051" StrongNumberX="1419" Language="H" Unicode="גָּד֥וֹל‎" nodeId="190760020070010" Length="1">G.FDO71WL</Node>
              </Node>
            </Node>
            <Node Id="9.11" Cat="S" Start="7" End="8" Rule="Np2S" Head="0" Language="H" nodeId="190760020080021" Length="2">
              <Node Id="9.12" Cat="np" Start="7" End="8" Rule="NPofNP" Head="0" Language="H" nodeId="190760020080020" Length="2">
                <Node Id="9.13" Cat="np" Start="7" End="7" Rule="N2NP" Head="0" Language="H" nodeId="190760020080011" Length="1">
                  <Node Id="9.14" Cat="noun" Start="7" End="7" Lemma="$&quot;M_1" UnicodeLemma="שֵׁם_1" English="name of" Analysis="ncmsc" morphId="190760020061" StrongNumberX="8034" Language="H" Unicode="שְׁמ‎" nodeId="190760020080010" Length="1">$:M</Node>
                </Node>
                <Node Id="9.15" Cat="np" Start="8" End="8" Rule="Pron2NP" Head="0" Language="H" nodeId="190760020090011" Length="1">
                  <Node Id="9.16" Cat="pron" Start="8" End="8" Lemma="OW" UnicodeLemma="וֹ" English="him" Analysis="psn3ms" morphId="190760020062" StrongNumberX="2050c" Language="H" Unicode="׃‎ֽוֹ‎" nodeId="190760020090010" Length="1">O75W00</Node>
                </Node>
              </Node>
            </Node>
          </Node>
        </Node>
      </Tree>
    </Trees>
  </Sentence>
  <Sentence ID="ps76:3">
    <Trees>
      <Tree>
        <Node Cat="S" Head="0" Start="0" End="10" nodeId="190760030010110" Length="11">
          <Node Id="1.1" Cat="cjp" Start="0" End="0" Rule="Cj2Cjp" Head="0" Language="H" nodeId="190760030010011" Length="1">
            <Node Id="1.2" Cat="cj" Start="0" End="0" Lemma="W:" UnicodeLemma="וְ" English="and" Analysis="Pc" morphId="190760030011" StrongNumberX="2050b" Language="H" Unicode="וַ‎" nodeId="190760030010010" Length="1">WA</Node>
          </Node>
          <Node Id="3.1" Cat="CL" Start="1" End="10" Rule="CLaCL" Head="0" Language="H" nodeId="190760030020100" Length="10">
            <Node Id="3.2" Cat="CL" Start="1" End="5" Rule="V-PP-S" Head="0" Language="H" nodeId="190760030020050" Length="5">
              <Node Id="3.3" Cat="V" Start="1" End="1" Rule="Vp2V" Head="0" Language="H" nodeId="190760030020012" Length="1">
                <Node Id="3.4" Cat="vp" Start="1" End="1" Rule="V2VP" Head="0" Language="H" nodeId="190760030020011" Length="1">
                  <Node Id="3.5" Cat="verb" Start="1" End="1" Lemma="HYH" UnicodeLemma="היה" English="he is" Analysis="vqw3msXa" morphId="190760030012" StrongNumberX="1961" Language="H" Unicode="יְהִ֣י‎" nodeId="190760030020010" Length="1">Y:HI74Y</Node>
                </Node>
              </Node>
              <Node Id="3.6" Cat="PP" Start="2" End="3" Rule="Pp2PP" Head="0" Language="H" nodeId="190760030030021" Length="2">
                <Node Id="3.7" Cat="pp" Start="2" End="3" Rule="PrepNp" Head="1" Language="H" nodeId="190760030030020" Length="2">
                  <Node Id="3.8" Cat="pp" Start="2" End="2" Rule="P2PP" Head="0" Language="H" nodeId="190760030030011" Length="1">
                    <Node Id="3.9" Cat="prep" Start="2" End="2" Lemma="B.:" UnicodeLemma="בְּ" English="in" Analysis="Pp" morphId="190760030021" StrongNumberX="0871a" Language="H" Unicode="בְ‎" nodeId="190760030030010" Length="1">B:</Node>
                  </Node>
                  <Node Id="3.10" Cat="np" Start="3" End="3" Rule="N2NP" Head="0" Language="H" nodeId="190760030040011" Length="1">
                    <Node Id="3.11" Cat="noun" Start="3" End="3" Lemma="$FL&quot;M_2" UnicodeLemma="שָׁלֵם_2" English="Salem" Analysis="np" morphId="190760030022" StrongNumberX="8004" Language="H" Unicode="שָׁלֵ֣ם‎" nodeId="190760030040010" Length="1">$FL"74M</Node>
                  </Node>
                </Node>
              </Node>
              <Node Id="3.12" Cat="S" Start="4" End="5" Rule="Np2S" Head="0" Language="H" nodeId="190760030050021" Length="2">
                <Node Id="3.13" Cat="np" Start="4" End="5" Rule="NPofNP" Head="0" Language="H" nodeId="190760030050020" Length="2">
                  <Node Id="3.14" Cat="np" Start="4" End="4" Rule="N2NP" Head="0" Language="H" nodeId="190760030050011" Length="1">
                    <Node Id="3.15" Cat="noun" Start="4" End="4" Lemma="SOK:" UnicodeLemma="סֹךְ" English="tent of" Analysis="ncmsc" morphId="190760030031" StrongNumberX="5520" Language="H" Unicode="סֻכּ‎" nodeId="190760030050010" Length="1">SUK.</Node>
                  </Node>
                  <Node Id="3.16" Cat="np" Start="5" End="5" Rule="Pron2NP" Head="0" Language="H" nodeId="190760030060011" Length="1">
                    <Node Id="3.17" Cat="pron" Start="5" End="5" Lemma="OW" UnicodeLemma="וֹ" English="him" Analysis="psn3ms" morphId="190760030032" StrongNumberX="2050c" Language="H" Unicode="֑וֹ‎" nodeId="190760030060010" Length="1">O92W</Node>
                  </Node>
                </Node>
              </Node>
            </Node>
            <Node Id="3.18" Cat="cjp" Start="6" End="6" Rule="Cj2Cjp" Head="0" Language="H" nodeId="190760030070011" Length="1">
              <Node Id="3.19" Cat="cj" Start="6" End="6" Lemma="W:" UnicodeLemma="וְ" English="and" Analysis="Pc" morphId="190760030041" StrongNumberX="2050b" Language="H" Unicode="וּ‎" nodeId="190760030070010" Length="1">W.</Node>
            </Node>
            <Node Id="3.20" Cat="CL" Start="7" End="10" Rule="S-PP" Head="0" Language="H" nodeId="190760030080040" Length="4">
              <Node Id="3.21" Cat="S" Start="7" End="8" Rule="Np2S" Head="0" Language="H" nodeId="190760030080021" Length="2">
                <Node Id="3.22" Cat="np" Start="7" End="8" Rule="NPofNP" Head="0" Language="H" nodeId="190760030080020" Length="2">
                  <Node Id="3.23" Cat="np" Start="7" End="7" Rule="N2NP" Head="0" Language="H" nodeId="190760030080011" Length="1">
                    <Node Id="3.24" Cat="noun" Start="7" End="7" Lemma="M:(ONFH" UnicodeLemma="מְעֹנָה" English="dwelling place of" Analysis="ncfsc" morphId="190760030042" StrongNumberX="4585" Language="H" Unicode="מְע֖וֹנָת‎" nodeId="190760030080010" Length="1">M:(O73WNFT</Node>
                  </Node>
                  <Node Id="3.25" Cat="np" Start="8" End="8" Rule="Pron2NP" Head="0" Language="H" nodeId="190760030090011" Length="1">
                    <Node Id="3.26" Cat="pron" Start="8" End="8" Lemma="OW" UnicodeLemma="וֹ" English="him" Analysis="psn3ms" morphId="190760030043" StrongNumberX="2050c" Language="H" Unicode="֣וֹ‎" nodeId="190760030090010" Length="1">O74W</Node>
                  </Node>
                </Node>
              </Node>
              <Node Id="3.27" Cat="PP" Start="9" End="10" Rule="Pp2PP" Head="0" Language="H" nodeId="190760030100021" Length="2">
                <Node Id="3.28" Cat="pp" Start="9" End="10" Rule="PrepNp" Head="1" Language="H" nodeId="190760030100020" Length="2">
                  <Node Id="3.29" Cat="pp" Start="9" End="9" Rule="P2PP" Head="0" Language="H" nodeId="190760030100011" Length="1">
                    <Node Id="3.30" Cat="prep" Start="9" End="9" Lemma="B.:" UnicodeLemma="בְּ" English="in" Analysis="Pp" morphId="190760030051" StrongNumberX="0871a" Language="H" Unicode="בְ‎" nodeId="190760030100010" Length="1">B:</Node>
                  </Node>
                  <Node Id="3.31" Cat="np" Start="10" End="10" Rule="N2NP" Head="0" Language="H" nodeId="190760030110011" Length="1">
                    <Node Id="3.32" Cat="noun" Start="10" End="10" Lemma="CIY.OWN" UnicodeLemma="צִיּוֹן" English="Zion" Analysis="np" morphId="190760030052" StrongNumberX="6726" Language="H" Unicode="׃‎צִיּֽוֹן‎" nodeId="190760030110010" Length="1">CIY.O75WN00</Node>
                  </Node>
                </Node>
              </Node>
            </Node>
          </Node>
        </Node>
      </Tree>
    </Trees>
  </Sentence>
  <Sentence ID="ps76:4">
    <Trees>
      <Tree>
        <Node Cat="S" Head="0" Start="0" End="10" nodeId="190760040010110" Length="11">
          <Node Id="4.1" Cat="CL" Start="0" End="9" Rule="ADV-V-O" Head="1" Language="H" nodeId="190760040010100" Length="10">
            <Node Id="4.2" Cat="ADV" Start="0" End="1" Rule="Advp2ADV" Head="0" Language="H" nodeId="190760040010021" Length="2">
              <Node Id="4.3" Cat="advp" Start="0" End="1" Rule="AdvX" Head="0" Language="H" nodeId="190760040010020" Length="2">
                <Node Id="4.4" Cat="adv" Start="0" End="0" Lemma="$FM" UnicodeLemma="שָׁם" English="~there" Analysis="Pd" morphId="190760040011" StrongNumberX="8033" Language="H" Unicode="שָׁ֭מּ‎" nodeId="190760040010010" Length="1">13$FM.</Node>
                <Node Id="4.5" Cat="x" Start="1" End="1" Lemma="FH" UnicodeLemma="ָה" English="at" Analysis="Xd" morphId="190760040012" StrongNumberX="1886c" Language="H" Unicode="ָה‎" nodeId="190760040020010" Length="1">FH</Node>
              </Node>
            </Node>
            <Node Id="4.6" Cat="V" Start="2" End="2" Rule="Vp2V" Head="0" Language="H" nodeId="190760040030012" Length="1">
              <Node Id="4.7" Cat="vp" Start="2" End="2" Rule="V2VP" Head="0" Language="H" nodeId="190760040030011" Length="1">
                <Node Id="4.8" Cat="verb" Start="2" End="2" Lemma="$BR_1" UnicodeLemma="שׁבר_1" English="he broke" Analysis="vpp3ms" morphId="190760040021" StrongNumberX="7665" Language="H" Unicode="שִׁבַּ֣ר‎" nodeId="190760040030010" Length="1">$IB.A74R</Node>
              </Node>
            </Node>
            <Node Id="4.9" Cat="O" Start="3" End="9" Rule="Np2O" Head="0" Language="H" nodeId="190760040040071" Length="7">
              <Node Id="4.10" Cat="np" Start="3" End="9" Rule="2NpaNpaNp" Head="0" Language="H" nodeId="190760040040070" Length="7">
                <Node Id="4.11" Cat="np" Start="3" End="4" Rule="NPofNP" Head="0" Language="H" nodeId="190760040040020" Length="2">
                  <Node Id="4.12" Cat="np" Start="3" End="3" Rule="N2NP" Head="0" Language="H" nodeId="190760040040011" Length="1">
                    <Node Id="4.13" Cat="noun" Start="3" End="3" Lemma="RE$EP_1" UnicodeLemma="רֶשֶׁף_1" English="flashes of" Analysis="ncmpc" morphId="190760040031" StrongNumberX="7565" Language="H" Unicode="רִשְׁפֵי־‎" nodeId="190760040040010" Length="1">RI$:P"Y-</Node>
                  </Node>
                  <Node Id="4.14" Cat="np" Start="4" End="4" Rule="N2NP" Head="0" Language="H" nodeId="190760040050011" Length="1">
                    <Node Id="4.15" Cat="noun" Start="4" End="4" Lemma="QE$ET" UnicodeLemma="קֶשֶׁת" English="arrow" Analysis="ncfsa" morphId="190760040041" StrongNumberX="7198" Language="H" Unicode="קָ֑שֶׁת‎" nodeId="190760040050010" Length="1">QF92$ET</Node>
                  </Node>
                </Node>
                <Node Id="4.16" Cat="np" Start="5" End="5" Rule="N2NP" Head="0" Language="H" nodeId="190760040060011" Length="1">
                  <Node Id="4.17" Cat="noun" Start="5" End="5" Lemma="MFG&quot;N_1" UnicodeLemma="מָגֵן_1" English="shield" Analysis="ncbsa" morphId="190760040051" StrongNumberX="4043" Language="H" Unicode="מָגֵ֬ן‎" nodeId="190760040060010" Length="1">MFG"64N</Node>
                </Node>
                <Node Id="4.18" Cat="cjp" Start="6" End="6" Rule="Cj2Cjp" Head="0" Language="H" nodeId="190760040070011" Length="1">
                  <Node Id="4.19" Cat="cj" Start="6" End="6" Lemma="W:" UnicodeLemma="וְ" English="and" Analysis="Pc" morphId="190760040061" StrongNumberX="2050b" Language="H" Unicode="וְ‎" nodeId="190760040070010" Length="1">W:</Node>
                </Node>
                <Node Id="4.20" Cat="np" Start="7" End="7" Rule="N2NP" Head="0" Language="H" nodeId="190760040080011" Length="1">
                  <Node Id="4.21" Cat="noun" Start="7" End="7" Lemma="XEREB" UnicodeLemma="חֶרֶב" English="sword" Analysis="ncfsa" morphId="190760040062" StrongNumberX="2719" Language="H" Unicode="חֶ֖רֶב‎" nodeId="190760040080010" Length="1">XE73REB</Node>
                </Node>
                <Node Id="4.22" Cat="cjp" Start="8" End="8" Rule="Cj2Cjp" Head="0" Language="H" nodeId="190760040090011" Length="1">
                  <Node Id="4.23" Cat="cj" Start="8" End="8" Lemma="W:" UnicodeLemma="וְ" English="and" Analysis="Pc" morphId="190760040071" StrongNumberX="2050b" Language="H" Unicode="וּ‎" nodeId="190760040090010" Length="1">W.</Node>
                </Node>
                <Node Id="4.24" Cat="np" Start="9" End="9" Rule="N2NP" Head="0" Language="H" nodeId="190760040100011" Length="1">
                  <Node Id="4.25" Cat="noun" Start="9" End="9" Lemma="MIL:XFMFH" UnicodeLemma="מִלְחָמָה" English="weapon of war" Analysis="ncfsa" morphId="190760040072" StrongNumberX="4421" Language="H" Unicode="מִלְחָמָ֣ה‎" nodeId="190760040100010" Length="1">MIL:XFMF74H</Node>
                </Node>
              </Node>
            </Node>
          </Node>
          <Node Id="22.1" Cat="CL" Start="10" End="10" Rule="Intj2CL" Head="0" Language="H" nodeId="190760040110012" Length="1">
            <Node Id="22.2" Cat="ijp" Start="10" End="10" Rule="Ij2Ijp" Head="0" Language="H" nodeId="190760040110011" Length="1">
              <Node Id="22.3" Cat="ij" Start="10" End="10" Lemma="SELFH" UnicodeLemma="סֶלָה" English="selah" Analysis="Pi" morphId="190760040081" StrongNumberX="5542" Language="H" Unicode="׃‎סֶֽלָה‎" nodeId="190760040110010" Length="1">SE75LFH00</Node>
            </Node>
          </Node>
        </Node>
      </Tree>
    </Trees>
  </Sentence>
  <Sentence ID="ps76:5">
    <Trees>
      <Tree>
        <Node Cat="S" Head="0" Start="0" End="5" nodeId="190760050010060" Length="6">
          <Node Id="1.1" Cat="CL" Start="0" End="1" Rule="P-S" Head="0" Language="H" nodeId="190760050010020" Length="2">
            <Node Id="1.2" Cat="P" Start="0" End="0" Rule="Adjp2P" Head="0" Language="H" nodeId="190760050010013" Length="1">
              <Node Id="1.3" Cat="adjp" Start="0" End="0" Rule="V2ADJP" Head="0" Language="H" nodeId="190760050010012" Length="1">
                <Node Id="1.4" Cat="vp" Start="0" End="0" Rule="V2VP" Head="0" Language="H" nodeId="190760050010011" Length="1">
                  <Node Id="1.5" Cat="verb" Start="0" End="0" Lemma=")WR" UnicodeLemma="אור" English="one giving light" Analysis="vnPmsa" morphId="190760050011" StrongNumberX="0215" Language="H" Unicode="נָ֭אוֹר‎" nodeId="190760050010010" Length="1">13NF)OWR</Node>
                </Node>
              </Node>
            </Node>
            <Node Id="1.6" Cat="S" Start="1" End="1" Rule="Np2S" Head="0" Language="H" nodeId="190760050020012" Length="1">
              <Node Id="1.7" Cat="np" Start="1" End="1" Rule="Pron2NP" Head="0" Language="H" nodeId="190760050020011" Length="1">
                <Node Id="1.8" Cat="pron" Start="1" End="1" Lemma=")AT.FH" UnicodeLemma="אַתָּה" English="you" Analysis="pi2ms" morphId="190760050021" StrongNumberX="0859" Language="H" Unicode="אַתָּ֥ה‎" nodeId="190760050020010" Length="1">)AT.F71H</Node>
              </Node>
            </Node>
          </Node>
          <Node Id="3.1" Cat="CL" Start="2" End="5" Rule="P-PP" Head="0" Language="H" nodeId="190760050030040" Length="4">
            <Node Id="3.2" Cat="P" Start="2" End="2" Rule="Adjp2P" Head="0" Language="H" nodeId="190760050030012" Length="1">
              <Node Id="3.3" Cat="adjp" Start="2" End="2" Rule="Adj2Adjp" Head="0" Language="H" nodeId="190760050030011" Length="1">
                <Node Id="3.4" Cat="adj" Start="2" End="2" Lemma=")AD.IYR" UnicodeLemma="אַדִּיר" English="majestic" Analysis="amsa" morphId="190760050031" StrongNumberX="0117" Language="H" Unicode="אַדִּ֗יר‎" nodeId="190760050030010" Length="1">)AD.I81YR</Node>
              </Node>
            </Node>
            <Node Id="3.5" Cat="PP" Start="3" End="5" Rule="Pp2PP" Head="0" Language="H" nodeId="190760050040031" Length="3">
              <Node Id="3.6" Cat="pp" Start="3" End="5" Rule="PrepNp" Head="1" Language="H" nodeId="190760050040030" Length="3">
                <Node Id="3.7" Cat="pp" Start="3" End="3" Rule="P2PP" Head="0" Language="H" nodeId="190760050040011" Length="1">
                  <Node Id="3.8" Cat="prep" Start="3" End="3" Lemma="MIN" UnicodeLemma="מִן" English="more than" Analysis="Pp" morphId="190760050041" StrongNumberX="4480" Language="H" Unicode="מֵֽ‎" nodeId="190760050040010" Length="1">M"75</Node>
                </Node>
                <Node Id="3.9" Cat="np" Start="4" End="5" Rule="NPofNP" Head="0" Language="H" nodeId="190760050050020" Length="2">
                  <Node Id="3.10" Cat="np" Start="4" End="4" Rule="N2NP" Head="0" Language="H" nodeId="190760050050011" Length="1">
                    <Node Id="3.11" Cat="noun" Start="4" End="4" Lemma="HAR" UnicodeLemma="הַר" English="mountains of" Analysis="ncmpc" morphId="190760050042" StrongNumberX="2022" Language="H" Unicode="הַרְרֵי־‎" nodeId="190760050050010" Length="1">HAR:R"Y-</Node>
                  </Node>
                  <Node Id="3.12" Cat="np" Start="5" End="5" Rule="N2NP" Head="0" Language="H" nodeId="190760050060011" Length="1">
                    <Node Id="3.13" Cat="noun" Start="5" End="5" Lemma="+EREP" UnicodeLemma="טֶרֶף" English="game" Analysis="ncmsa" morphId="190760050051" StrongNumberX="2964" Language="H" Unicode="׃‎טָֽרֶף‎" nodeId="190760050060010" Length="1">+F75REP00</Node>
                  </Node>
                </Node>
              </Node>
            </Node>
          </Node>
        </Node>
      </Tree>
    </Trees>
  </Sentence>
  <Sentence ID="ps76:6">
    <Trees>
      <Tree>
        <Node Cat="S" Head="0" Start="0" End="13" nodeId="190760060010140" Length="14">
          <Node Id="2.1" Cat="CL" Start="0" End="2" Rule="V-S" Head="0" Language="H" nodeId="190760060010030" Length="3">
            <Node Id="2.2" Cat="V" Start="0" End="0" Rule="Vp2V" Head="0" Language="H" nodeId="190760060010012" Length="1">
              <Node Id="2.3" Cat="vp" Start="0" End="0" Rule="V2VP" Head="0" Language="H" nodeId="190760060010011" Length="1">
                <Node Id="2.4" Cat="verb" Start="0" End="0" Lemma="$LL_2" UnicodeLemma="שׁלל_2" English="they lie plundered" Analysis="vyp3cp" morphId="190760060011" StrongNumberX="7997" Language="H" Unicode="אֶשְׁתּוֹלְל֨וּ ׀‎" nodeId="190760060010010" Length="1">)E$:T.OWL:L63W.05</Node>
              </Node>
            </Node>
            <Node Id="2.5" Cat="S" Start="1" End="2" Rule="Np2S" Head="0" Language="H" nodeId="190760060020021" Length="2">
              <Node Id="2.6" Cat="np" Start="1" End="2" Rule="NPofNP" Head="0" Language="H" nodeId="190760060020020" Length="2">
                <Node Id="2.7" Cat="np" Start="1" End="1" Rule="Adj2NP" Head="0" Language="H" nodeId="190760060020012" Length="1">
                  <Node Id="2.8" Cat="adjp" Start="1" End="1" Rule="Adj2Adjp" Head="0" Language="H" nodeId="190760060020011" Length="1">
                    <Node Id="2.9" Cat="adj" Start="1" End="1" Lemma=")AB.IYR" UnicodeLemma="אַבִּיר" English="men valiant of" Analysis="ampc" morphId="190760060021" StrongNumberX="0047" Language="H" Unicode="אַבִּ֣ירֵי‎" nodeId="190760060020010" Length="1">)AB.I74YR"Y</Node>
                  </Node>
                </Node>
                <Node Id="2.10" Cat="np" Start="2" End="2" Rule="N2NP" Head="0" Language="H" nodeId="190760060030011" Length="1">
                  <Node Id="2.11" Cat="noun" Start="2" End="2" Lemma="L&quot;B" UnicodeLemma="לֵב" English="heart" Analysis="ncmsa" morphId="190760060031" StrongNumberX="3820" Language="H" Unicode="לֵ֭ב‎" nodeId="190760060030010" Length="1">13L"B</Node>
                </Node>
              </Node>
            </Node>
          </Node>
          <Node Id="9.1" Cat="CL" Start="3" End="5" Rule="V-O" Head="0" Language="H" nodeId="190760060040030" Length="3">
            <Node Id="9.2" Cat="V" Start="3" End="3" Rule="Vp2V" Head="0" Language="H" nodeId="190760060040012" Length="1">
              <Node Id="9.3" Cat="vp" Start="3" End="3" Rule="V2VP" Head="0" Language="H" nodeId="190760060040011" Length="1">
                <Node Id="9.4" Cat="verb" Start="3" End="3" Lemma="NWM" UnicodeLemma="נום" English="they sleep" Analysis="vqp3cp" morphId="190760060041" StrongNumberX="5123" Language="H" Unicode="נָמ֣וּ‎" nodeId="190760060040010" Length="1">NFM74W.</Node>
              </Node>
            </Node>
            <Node Id="9.5" Cat="O" Start="4" End="5" Rule="Np2O" Head="0" Language="H" nodeId="190760060050021" Length="2">
              <Node Id="9.6" Cat="np" Start="4" End="5" Rule="NPofNP" Head="0" Language="H" nodeId="190760060050020" Length="2">
                <Node Id="9.7" Cat="np" Start="4" End="4" Rule="N2NP" Head="0" Language="H" nodeId="190760060050011" Length="1">
                  <Node Id="9.8" Cat="noun" Start="4" End="4" Lemma="$&quot;NFH" UnicodeLemma="שֵׁנָה" English="sleep of" Analysis="ncfsc" morphId="190760060051" StrongNumberX="8142" Language="H" Unicode="שְׁנָת‎" nodeId="190760060050010" Length="1">$:NFT</Node>
                </Node>
                <Node Id="9.9" Cat="np" Start="5" End="5" Rule="Pron2NP" Head="0" Language="H" nodeId="190760060060011" Length="1">
                  <Node Id="9.10" Cat="pron" Start="5" End="5" Lemma="FM" UnicodeLemma="ָמ" English="them" Analysis="psn3mp" morphId="190760060052" StrongNumberX="3963a" Language="H" Unicode="ָ֑ם‎" nodeId="190760060060010" Length="1">F92M</Node>
                </Node>
              </Node>
            </Node>
          </Node>
          <Node Id="13.1" Cat="cjp" Start="6" End="6" Rule="Cj2Cjp" Head="0" Language="H" nodeId="190760060070011" Length="1">
            <Node Id="13.2" Cat="cj" Start="6" End="6" Lemma="W:" UnicodeLemma="וְ" English="and" Analysis="Pc" morphId="190760060061" StrongNumberX="2050b" Language="H" Unicode="וְ‎" nodeId="190760060070010" Length="1">W:</Node>
          </Node>
          <Node Id="15.1" Cat="CL" Start="7" End="13" Rule="ADV-V-S-O" Head="1" Language="H" nodeId="190760060080070" Length="7">
            <Node Id="15.2" Cat="ADV" Start="7" End="7" Rule="Advp2ADV" Head="0" Language="H" nodeId="190760060080012" Length="1">
              <Node Id="15.3" Cat="advp" Start="7" End="7" Rule="Adv2Advp" Head="0" Language="H" nodeId="190760060080011" Length="1">
                <Node Id="15.4" Cat="adv" Start="7" End="7" Lemma="LO)" UnicodeLemma="לֹא" English="not" Analysis="Pn" morphId="190760060062" StrongNumberX="3808" Language="H" Unicode="לֹא־‎" nodeId="190760060080010" Length="1">LO)-</Node>
              </Node>
            </Node>
            <Node Id="15.5" Cat="V" Start="8" End="8" Rule="Vp2V" Head="0" Language="H" nodeId="190760060090012" Length="1">
              <Node Id="15.6" Cat="vp" Start="8" End="8" Rule="V2VP" Head="0" Language="H" nodeId="190760060090011" Length="1">
                <Node Id="15.7" Cat="verb" Start="8" End="8" Lemma="MC)" UnicodeLemma="מצא" English="they can lift" Analysis="vqp3cp" morphId="190760060071" StrongNumberX="4672" Language="H" Unicode="מָצְא֖וּ‎" nodeId="190760060090010" Length="1">MFC:)73W.</Node>
              </Node>
            </Node>
            <Node Id="15.8" Cat="S" Start="9" End="11" Rule="Np2S" Head="0" Language="H" nodeId="190760060100031" Length="3">
              <Node Id="15.9" Cat="np" Start="9" End="11" Rule="QuanNP" Head="1" Language="H" nodeId="190760060100030" Length="3">
                <Node Id="15.10" Cat="np" Start="9" End="9" Rule="N2NP" Head="0" Language="H" nodeId="190760060100011" Length="1">
                  <Node Id="15.11" Cat="noun" Start="9" End="9" Lemma="K.OL" UnicodeLemma="כֹּל" English="any of" Analysis="ncmsc" morphId="190760060081" StrongNumberX="3605" Language="H" Unicode="כָל־‎" nodeId="190760060100010" Length="1">KFL-</Node>
                </Node>
                <Node Id="15.12" Cat="np" Start="10" End="11" Rule="NPofNP" Head="0" Language="H" nodeId="190760060110020" Length="2">
                  <Node Id="15.13" Cat="np" Start="10" End="10" Rule="N2NP" Head="0" Language="H" nodeId="190760060110011" Length="1">
                    <Node Id="15.14" Cat="noun" Start="10" End="10" Lemma=")IY$" UnicodeLemma="אִישׁ" English="men of" Analysis="ncmpc" morphId="190760060091" StrongNumberX="0376" Language="H" Unicode="אַנְשֵׁי־‎" nodeId="190760060110010" Length="1">)AN:$"Y-</Node>
                  </Node>
                  <Node Id="15.15" Cat="np" Start="11" End="11" Rule="N2NP" Head="0" Language="H" nodeId="190760060120011" Length="1">
                    <Node Id="15.16" Cat="noun" Start="11" End="11" Lemma="XAYIL" UnicodeLemma="חַיִל" English="war" Analysis="ncmsa" morphId="190760060101" StrongNumberX="2428" Language="H" Unicode="חַ֣יִל‎" nodeId="190760060120010" Length="1">XA74YIL</Node>
                  </Node>
                </Node>
              </Node>
            </Node>
            <Node Id="15.17" Cat="O" Start="12" End="13" Rule="Np2O" Head="0" Language="H" nodeId="190760060130021" Length="2">
              <Node Id="15.18" Cat="np" Start="12" End="13" Rule="NPofNP" Head="0" Language="H" nodeId="190760060130020" Length="2">
                <Node Id="15.19" Cat="np" Start="12" End="12" Rule="N2NP" Head="0" Language="H" nodeId="190760060130011" Length="1">
                  <Node Id="15.20" Cat="noun" Start="12" End="12" Lemma="YFD" UnicodeLemma="יָד" English="hands of" Analysis="ncfdc" morphId="190760060111" StrongNumberX="3027" Language="H" Unicode="יְדֵי‎" nodeId="190760060130010" Length="1">Y:D"Y</Node>
                </Node>
                <Node Id="15.21" Cat="np" Start="13" End="13" Rule="Pron2NP" Head="0" Language="H" nodeId="190760060140011" Length="1">
                  <Node Id="15.22" Cat="pron" Start="13" End="13" Lemma="FM" UnicodeLemma="ָמ" English="them" Analysis="psn3mp" morphId="190760060112" StrongNumberX="3963a" Language="H" Unicode="׃‎הֶֽם‎" nodeId="190760060140010" Length="1">HE75M00</Node>
                </Node>
              </Node>
            </Node>
          </Node>
        </Node>
      </Tree>
    </Trees>
  </Sentence>
  <Sentence ID="ps76:7">
    <Trees>
      <Tree>
        <Node Cat="S" Head="0" Start="0" End="9" nodeId="190760070010101" Length="10">
          <Node Id="1.1" Cat="CL" Start="0" End="9" Rule="ClCl2" Head="1" Language="H" nodeId="190760070010100" Length="10">
            <Node Id="1.2" Cat="CL" Start="0" End="1" Rule="Np2CL" Head="0" Language="H" nodeId="190760070010021" Length="2">
              <Node Id="1.3" Cat="np" Start="0" End="1" Rule="NPofNP" Head="0" Language="H" nodeId="190760070010020" Length="2">
                <Node Id="1.4" Cat="np" Start="0" End="0" Rule="N2NP" Head="0" Language="H" nodeId="190760070010011" Length="1">
                  <Node Id="1.5" Cat="noun" Start="0" End="0" Lemma="):ELOHIYM" UnicodeLemma="אֱלֹהִים" English="God of" Analysis="ncmpc" morphId="190760070021" StrongNumberX="0430" Language="H" Unicode="אֱלֹהֵ֣י‎" nodeId="190760070010010" Length="1">):ELOH"74Y</Node>
                </Node>
                <Node Id="1.6" Cat="np" Start="1" End="1" Rule="N2NP" Head="0" Language="H" nodeId="190760070020011" Length="1">
                  <Node Id="1.7" Cat="noun" Start="1" End="1" Lemma="YA(:AQOB" UnicodeLemma="יַעֲקֹב" English="Jacob" Analysis="np" morphId="190760070031" StrongNumberX="3290" Language="H" Unicode="יַעֲקֹ֑ב‎" nodeId="190760070020010" Length="1">YA(:AQO92B</Node>
                </Node>
              </Node>
            </Node>
            <Node Id="1.8" Cat="CL" Start="2" End="9" Rule="PP-V-S" Head="1" Language="H" nodeId="190760070030080" Length="8">
              <Node Id="1.9" Cat="PP" Start="2" End="4" Rule="Pp2PP" Head="0" Language="H" nodeId="190760070030031" Length="3">
                <Node Id="1.10" Cat="pp" Start="2" End="4" Rule="PrepNp" Head="1" Language="H" nodeId="190760070030030" Length="3">
                  <Node Id="1.11" Cat="pp" Start="2" End="2" Rule="P2PP" Head="0" Language="H" nodeId="190760070030011" Length="1">
                    <Node Id="1.12" Cat="prep" Start="2" End="2" Lemma="MIN" UnicodeLemma="מִן" English="at" Analysis="Pp" morphId="190760070011" StrongNumberX="4480" Language="H" Unicode="מִ֭‎" nodeId="190760070030010" Length="1">13MI</Node>
                  </Node>
                  <Node Id="1.13" Cat="np" Start="3" End="4" Rule="NPofNP" Head="0" Language="H" nodeId="190760070040020" Length="2">
                    <Node Id="1.14" Cat="np" Start="3" End="3" Rule="N2NP" Head="0" Language="H" nodeId="190760070040011" Length="1">
                      <Node Id="1.15" Cat="noun" Start="3" End="3" Lemma="G.:(FRFH" UnicodeLemma="גְּעָרָה" English="rebuke of" Analysis="ncfsc" morphId="190760070012" StrongNumberX="1606" Language="H" Unicode="גַּעֲרָ֣ת‎" nodeId="190760070040010" Length="1">G.A(:ARF74T</Node>
                    </Node>
                    <Node Id="1.16" Cat="np" Start="4" End="4" Rule="Pron2NP" Head="0" Language="H" nodeId="190760070050011" Length="1">
                      <Node Id="1.17" Cat="pron" Start="4" End="4" Lemma=":KF" UnicodeLemma="ְכָ" English="you" Analysis="psn2ms" morphId="190760070013" StrongNumberX="3509b" Language="H" Unicode="ְךָ‎" nodeId="190760070050010" Length="1">:KF</Node>
                    </Node>
                  </Node>
                </Node>
              </Node>
              <Node Id="1.18" Cat="V" Start="5" End="5" Rule="Vp2V" Head="0" Language="H" nodeId="190760070060012" Length="1">
                <Node Id="1.19" Cat="vp" Start="5" End="5" Rule="V2VP" Head="0" Language="H" nodeId="190760070060011" Length="1">
                  <Node Id="1.20" Cat="verb" Start="5" End="5" Lemma="RDM" UnicodeLemma="רדם" English="one lying still" Analysis="vnPmsa" morphId="190760070041" StrongNumberX="7290" Language="H" Unicode="נִ֝רְדָּ֗ם‎" nodeId="190760070060010" Length="1">11NIR:D.F81M</Node>
                </Node>
              </Node>
              <Node Id="1.21" Cat="S" Start="6" End="9" Rule="Np2S" Head="0" Language="H" nodeId="190760070070041" Length="4">
                <Node Id="1.22" Cat="np" Start="6" End="9" Rule="aNpaNp" Head="1" Language="H" nodeId="190760070070040" Length="4">
                  <Node Id="1.23" Cat="cjp" Start="6" End="6" Rule="Cj2Cjp" Head="0" Language="H" nodeId="190760070070011" Length="1">
                    <Node Id="1.24" Cat="cj" Start="6" End="6" Lemma="W:" UnicodeLemma="וְ" English="both" Analysis="Pc" morphId="190760070051" StrongNumberX="2050b" Language="H" Unicode="וְ‎" nodeId="190760070070010" Length="1">W:</Node>
                  </Node>
                  <Node Id="1.25" Cat="np" Start="7" End="7" Rule="N2NP" Head="0" Language="H" nodeId="190760070080011" Length="1">
                    <Node Id="1.26" Cat="noun" Start="7" End="7" Lemma="REKEB" UnicodeLemma="רֶכֶב" English="chariot" Analysis="ncmsa" morphId="190760070052" StrongNumberX="7393" Language="H" Unicode="רֶ֣כֶב‎" nodeId="190760070080010" Length="1">RE74KEB</Node>
                  </Node>
                  <Node Id="1.27" Cat="cjp" Start="8" End="8" Rule="Cj2Cjp" Head="0" Language="H" nodeId="190760070090011" Length="1">
                    <Node Id="1.28" Cat="cj" Start="8" End="8" Lemma="W:" UnicodeLemma="וְ" English="and" Analysis="Pc" morphId="190760070061" StrongNumberX="2050b" Language="H" Unicode="וָ‎" nodeId="190760070090010" Length="1">WF</Node>
                  </Node>
                  <Node Id="1.29" Cat="np" Start="9" End="9" Rule="N2NP" Head="0" Language="H" nodeId="190760070100011" Length="1">
                    <Node Id="1.30" Cat="noun" Start="9" End="9" Lemma="SW.S_1" UnicodeLemma="סוּס_1" English="horse" Analysis="ncmsa" morphId="190760070062" StrongNumberX="5483" Language="H" Unicode="׃‎סֽוּס‎" nodeId="190760070100010" Length="1">S75W.S00</Node>
                  </Node>
                </Node>
              </Node>
            </Node>
          </Node>
        </Node>
      </Tree>
    </Trees>
  </Sentence>
  <Sentence ID="ps76:8">
    <Trees>
      <Tree>
        <Node Cat="S" Head="0" Start="0" End="12" nodeId="190760080010130" Length="13">
          <Node Id="1.1" Cat="CL" Start="0" End="2" Rule="ClCl2" Head="1" Language="H" nodeId="190760080010030" Length="3">
            <Node Id="1.2" Cat="CL" Start="0" End="0" Rule="Np2CL" Head="0" Language="H" nodeId="190760080010012" Length="1">
              <Node Id="1.3" Cat="np" Start="0" End="0" Rule="Pron2NP" Head="0" Language="H" nodeId="190760080010011" Length="1">
                <Node Id="1.4" Cat="pron" Start="0" End="0" Lemma=")AT.FH" UnicodeLemma="אַתָּה" English="you" Analysis="pi2ms" morphId="190760080011" StrongNumberX="0859" Language="H" Unicode="אַתָּ֤ה ׀‎" nodeId="190760080010010" Length="1">)AT.F70H05</Node>
              </Node>
            </Node>
            <Node Id="1.5" Cat="CL" Start="1" End="2" Rule="V-S" Head="0" Language="H" nodeId="190760080020020" Length="2">
              <Node Id="1.6" Cat="V" Start="1" End="1" Rule="Vp2V" Head="0" Language="H" nodeId="190760080020012" Length="1">
                <Node Id="1.7" Cat="vp" Start="1" End="1" Rule="V2VP" Head="0" Language="H" nodeId="190760080020011" Length="1">
                  <Node Id="1.8" Cat="verb" Start="1" End="1" Lemma="YR)_1" UnicodeLemma="ירא_1" English="one being feared" Analysis="vnPmsa" morphId="190760080021" StrongNumberX="3372" Language="H" Unicode="נ֥וֹרָא‎" nodeId="190760080020010" Length="1">NO71WRF)</Node>
                </Node>
              </Node>
              <Node Id="1.9" Cat="S" Start="2" End="2" Rule="Np2S" Head="0" Language="H" nodeId="190760080030012" Length="1">
                <Node Id="1.10" Cat="np" Start="2" End="2" Rule="Pron2NP" Head="0" Language="H" nodeId="190760080030011" Length="1">
                  <Node Id="1.11" Cat="pron" Start="2" End="2" Lemma=")AT.FH" UnicodeLemma="אַתָּה" English="you" Analysis="pi2ms" morphId="190760080031" StrongNumberX="0859" Language="H" Unicode="אַ֗תָּה‎" nodeId="190760080030010" Length="1">)A81T.FH</Node>
                </Node>
              </Node>
            </Node>
          </Node>
          <Node Id="7.1" Cat="cjp" Start="3" End="3" Rule="Cj2Cjp" Head="0" Language="H" nodeId="190760080040011" Length="1">
            <Node Id="7.2" Cat="cj" Start="3" End="3" Lemma="W:" UnicodeLemma="וְ" English="and" Analysis="Pc" morphId="190760080041" StrongNumberX="2050b" Language="H" Unicode="וּ‎" nodeId="190760080040010" Length="1">W.</Node>
          </Node>
          <Node Id="9.1" Cat="CL" Start="4" End="12" Rule="S-V-PP-PP" Head="1" Language="H" nodeId="190760080050090" Length="9">
            <Node Id="9.2" Cat="S" Start="4" End="4" Rule="Np2S" Head="0" Language="H" nodeId="190760080050012" Length="1">
              <Node Id="9.3" Cat="np" Start="4" End="4" Rule="Pron2NP" Head="0" Language="H" nodeId="190760080050011" Length="1">
                <Node Id="9.4" Cat="pron" Start="4" End="4" Lemma="MIY" UnicodeLemma="מִי" English="who?" Analysis="pii" morphId="190760080042" StrongNumberX="4310" Language="H" Unicode="מִֽי־‎" nodeId="190760080050010" Length="1">MI75Y-</Node>
              </Node>
            </Node>
            <Node Id="9.5" Cat="V" Start="5" End="5" Rule="Vp2V" Head="0" Language="H" nodeId="190760080060012" Length="1">
              <Node Id="9.6" Cat="vp" Start="5" End="5" Rule="V2VP" Head="0" Language="H" nodeId="190760080060011" Length="1">
                <Node Id="9.7" Cat="verb" Start="5" End="5" Lemma="(MD" UnicodeLemma="עמד" English="he can stand" Analysis="vqi3ms" morphId="190760080051" StrongNumberX="5975" Language="H" Unicode="יַעֲמֹ֥ד‎" nodeId="190760080060010" Length="1">YA(:AMO71D</Node>
              </Node>
            </Node>
            <Node Id="9.8" Cat="PP" Start="6" End="8" Rule="Pp2PP" Head="0" Language="H" nodeId="190760080070031" Length="3">
              <Node Id="9.9" Cat="pp" Start="6" End="8" Rule="PrepNp" Head="1" Language="H" nodeId="190760080070030" Length="3">
                <Node Id="9.10" Cat="pp" Start="6" End="6" Rule="P2PP" Head="0" Language="H" nodeId="190760080070011" Length="1">
                  <Node Id="9.11" Cat="prep" Start="6" End="6" Lemma="L:" UnicodeLemma="לְ" English="before" Analysis="Pp" morphId="190760080061" StrongNumberX="3807a" Language="H" Unicode="לְ‎" nodeId="190760080070010" Length="1">L:</Node>
                </Node>
                <Node Id="9.12" Cat="np" Start="7" End="8" Rule="NPofNP" Head="0" Language="H" nodeId="190760080080020" Length="2">
                  <Node Id="9.13" Cat="np" Start="7" End="7" Rule="N2NP" Head="0" Language="H" nodeId="190760080080011" Length="1">
                    <Node Id="9.14" Cat="noun" Start="7" End="7" Lemma="P.FNEH" UnicodeLemma="פָּנֶה" English="" Analysis="ncbpc" morphId="190760080062" StrongNumberX="6440" Language="H" Unicode="פָנֶ֗י‎" nodeId="190760080080010" Length="1">PFNE81Y</Node>
                  </Node>
                  <Node Id="9.15" Cat="np" Start="8" End="8" Rule="Pron2NP" Head="0" Language="H" nodeId="190760080090011" Length="1">
                    <Node Id="9.16" Cat="pron" Start="8" End="8" Lemma=":KF" UnicodeLemma="ְכָ" English="you" Analysis="psn2ms" morphId="190760080063" StrongNumberX="3509b" Language="H" Unicode="ךָ‎" nodeId="190760080090010" Length="1">KF</Node>
                  </Node>
                </Node>
              </Node>
            </Node>
            <Node Id="9.17" Cat="PP" Start="9" End="12" Rule="Pp2PP" Head="0" Language="H" nodeId="190760080100041" Length="4">
              <Node Id="9.18" Cat="pp" Start="9" End="12" Rule="PrepNp" Head="1" Language="H" nodeId="190760080100040" Length="4">
                <Node Id="9.19" Cat="pp" Start="9" End="10" Rule="PpAdvp" Head="0" Language="H" nodeId="190760080100020" Length="2">
                  <Node Id="9.20" Cat="pp" Start="9" End="9" Rule="P2PP" Head="0" Language="H" nodeId="190760080100011" Length="1">
                    <Node Id="9.21" Cat="prep" Start="9" End="9" Lemma="MIN" UnicodeLemma="מִן" English="at" Analysis="Pp" morphId="190760080071" StrongNumberX="4480" Language="H" Unicode="מֵ‎" nodeId="190760080100010" Length="1">M"</Node>
                  </Node>
                  <Node Id="9.22" Cat="advp" Start="10" End="10" Rule="Adv2Advp" Head="0" Language="H" nodeId="190760080110011" Length="1">
                    <Node Id="9.23" Cat="adv" Start="10" End="10" Lemma=")FZ" UnicodeLemma="אָז" English="when" Analysis="Pd" morphId="190760080072" StrongNumberX="0227" Language="H" Unicode="אָ֥ז‎" nodeId="190760080110010" Length="1">)F71Z</Node>
                  </Node>
                </Node>
                <Node Id="9.24" Cat="np" Start="11" End="12" Rule="NPofNP" Head="0" Language="H" nodeId="190760080120020" Length="2">
                  <Node Id="9.25" Cat="np" Start="11" End="11" Rule="N2NP" Head="0" Language="H" nodeId="190760080120011" Length="1">
                    <Node Id="9.26" Cat="noun" Start="11" End="11" Lemma=")AP_2" UnicodeLemma="אַף_2" English="anger of" Analysis="ncmsc" morphId="190760080081" StrongNumberX="0639" Language="H" Unicode="אַפּ‎" nodeId="190760080120010" Length="1">)AP.</Node>
                  </Node>
                  <Node Id="9.27" Cat="np" Start="12" End="12" Rule="Pron2NP" Head="0" Language="H" nodeId="190760080130011" Length="1">
                    <Node Id="9.28" Cat="pron" Start="12" End="12" Lemma=":KF" UnicodeLemma="ְכָ" English="you" Analysis="psn2ms" morphId="190760080082" StrongNumberX="3509b" Language="H" Unicode="׃‎ֶֽךָ‎" nodeId="190760080130010" Length="1">E75KF00</Node>
                  </Node>
                </Node>
              </Node>
            </Node>
          </Node>
        </Node>
      </Tree>
    </Trees>
  </Sentence>
  <Sentence ID="ps76:9">
    <Trees>
      <Tree>
        <Node Cat="S" Head="0" Start="0" End="7" nodeId="190760090010080" Length="8">
          <Node Id="1.1" Cat="CL" Start="0" End="3" Rule="PP-V-O" Head="1" Language="H" nodeId="190760090010040" Length="4">
            <Node Id="1.2" Cat="PP" Start="0" End="1" Rule="Pp2PP" Head="0" Language="H" nodeId="190760090010021" Length="2">
              <Node Id="1.3" Cat="pp" Start="0" End="1" Rule="PrepNp" Head="1" Language="H" nodeId="190760090010020" Length="2">
                <Node Id="1.4" Cat="pp" Start="0" End="0" Rule="P2PP" Head="0" Language="H" nodeId="190760090010011" Length="1">
                  <Node Id="1.5" Cat="prep" Start="0" End="0" Lemma="MIN" UnicodeLemma="מִן" English="from" Analysis="Pp" morphId="190760090011" StrongNumberX="4480" Language="H" Unicode="מִ֭‎" nodeId="190760090010010" Length="1">13MI</Node>
                </Node>
                <Node Id="1.6" Cat="np" Start="1" End="1" Rule="N2NP" Head="0" Language="H" nodeId="190760090020011" Length="1">
                  <Node Id="1.7" Cat="noun" Start="1" End="1" Lemma="$FMAYIM" UnicodeLemma="שָׁמַיִם" English="heavens" Analysis="ncmpa" morphId="190760090012" StrongNumberX="8064" Language="H" Unicode="שָּׁמַיִם‎" nodeId="190760090020010" Length="1">$.FMAYIM</Node>
                </Node>
              </Node>
            </Node>
            <Node Id="1.8" Cat="V" Start="2" End="2" Rule="Vp2V" Head="0" Language="H" nodeId="190760090030012" Length="1">
              <Node Id="1.9" Cat="vp" Start="2" End="2" Rule="V2VP" Head="0" Language="H" nodeId="190760090030011" Length="1">
                <Node Id="1.10" Cat="verb" Start="2" End="2" Lemma="$M(" UnicodeLemma="שׁמע" English="you pronounced" Analysis="vhp2ms" morphId="190760090021" StrongNumberX="8085" Language="H" Unicode="הִשְׁמַ֣עְתָּ‎" nodeId="190760090030010" Length="1">HI$:MA74(:T.F</Node>
              </Node>
            </Node>
            <Node Id="1.11" Cat="O" Start="3" End="3" Rule="Np2O" Head="0" Language="H" nodeId="190760090040012" Length="1">
              <Node Id="1.12" Cat="np" Start="3" End="3" Rule="N2NP" Head="0" Language="H" nodeId="190760090040011" Length="1">
                <Node Id="1.13" Cat="noun" Start="3" End="3" Lemma="D.IYN" UnicodeLemma="דִּין" English="judgment" Analysis="ncmsa" morphId="190760090031" StrongNumberX="1779" Language="H" Unicode="דִּ֑ין‎" nodeId="190760090040010" Length="1">D.I92YN</Node>
              </Node>
            </Node>
          </Node>
          <Node Id="8.1" Cat="CL" Start="4" End="7" Rule="CLaCL" Head="0" Language="H" nodeId="190760090050040" Length="4">
            <Node Id="8.2" Cat="CL" Start="4" End="5" Rule="S-V" Head="1" Language="H" nodeId="190760090050020" Length="2">
              <Node Id="8.3" Cat="S" Start="4" End="4" Rule="Np2S" Head="0" Language="H" nodeId="190760090050012" Length="1">
                <Node Id="8.4" Cat="np" Start="4" End="4" Rule="N2NP" Head="0" Language="H" nodeId="190760090050011" Length="1">
                  <Node Id="8.5" Cat="noun" Start="4" End="4" Lemma=")EREC" UnicodeLemma="אֶרֶץ" English="land" Analysis="ncfsa" morphId="190760090041" StrongNumberX="0776" Language="H" Unicode="אֶ֖רֶץ‎" nodeId="190760090050010" Length="1">)E73REC</Node>
                </Node>
              </Node>
              <Node Id="8.6" Cat="V" Start="5" End="5" Rule="Vp2V" Head="0" Language="H" nodeId="190760090060012" Length="1">
                <Node Id="8.7" Cat="vp" Start="5" End="5" Rule="V2VP" Head="0" Language="H" nodeId="190760090060011" Length="1">
                  <Node Id="8.8" Cat="verb" Start="5" End="5" Lemma="YR)_1" UnicodeLemma="ירא_1" English="she feared" Analysis="vqp3fs" morphId="190760090051" StrongNumberX="3372" Language="H" Unicode="יָֽרְאָ֣ה‎" nodeId="190760090060010" Length="1">YF75R:)F74H</Node>
                </Node>
              </Node>
            </Node>
            <Node Id="8.9" Cat="cjp" Start="6" End="6" Rule="Cj2Cjp" Head="0" Language="H" nodeId="190760090070011" Length="1">
              <Node Id="8.10" Cat="cj" Start="6" End="6" Lemma="W:" UnicodeLemma="וְ" English="and" Analysis="Pc" morphId="190760090061" StrongNumberX="2050b" Language="H" Unicode="וְ‎" nodeId="190760090070010" Length="1">W:</Node>
            </Node>
            <Node Id="8.11" Cat="CL" Start="7" End="7" Rule="V2CL" Head="0" Language="H" nodeId="190760090080013" Length="1">
              <Node Id="8.12" Cat="V" Start="7" End="7" Rule="Vp2V" Head="0" Language="H" nodeId="190760090080012" Length="1">
                <Node Id="8.13" Cat="vp" Start="7" End="7" Rule="V2VP" Head="0" Language="H" nodeId="190760090080011" Length="1">
                  <Node Id="8.14" Cat="verb" Start="7" End="7" Lemma="$Q+" UnicodeLemma="שׁקט" English="she was quiet" Analysis="vqp3fs" morphId="190760090062" StrongNumberX="8252" Language="H" Unicode="׃‎שָׁקָֽטָה‎" nodeId="190760090080010" Length="1">$FQF75+FH00</Node>
                </Node>
              </Node>
            </Node>
          </Node>
        </Node>
      </Tree>
    </Trees>
  </Sentence>
  <Sentence ID="ps76:10">
    <Trees>
      <Tree>
        <Node Cat="S" Head="0" Start="0" End="11" nodeId="190760100010120" Length="12">
          <Node Id="7.1" Cat="CL" Start="0" End="10" Rule="PP2CL" Head="0" Language="H" nodeId="190760100010112" Length="11">
            <Node Id="7.2" Cat="PP" Start="0" End="10" Rule="Pp2PP" Head="0" Language="H" nodeId="190760100010111" Length="11">
              <Node Id="7.3" Cat="pp" Start="0" End="10" Rule="PrepCL" Head="1" Language="H" nodeId="190760100010110" Length="11">
                <Node Id="7.4" Cat="pp" Start="0" End="0" Rule="P2PP" Head="0" Language="H" nodeId="190760100010011" Length="1">
                  <Node Id="7.5" Cat="prep" Start="0" End="0" Lemma="B.:" UnicodeLemma="בְּ" English="when" Analysis="Pp" morphId="190760100011" StrongNumberX="0871a" Language="H" Unicode="בְּ‎" nodeId="190760100010010" Length="1">B.:</Node>
                </Node>
                <Node Id="7.6" Cat="CL" Start="1" End="10" Rule="V-PP-S-PP" Head="0" Language="H" nodeId="190760100020100" Length="10">
                  <Node Id="7.7" Cat="V" Start="1" End="1" Rule="Vp2V" Head="0" Language="H" nodeId="190760100020012" Length="1">
                    <Node Id="7.8" Cat="vp" Start="1" End="1" Rule="V2VP" Head="0" Language="H" nodeId="190760100020011" Length="1">
                      <Node Id="7.9" Cat="verb" Start="1" End="1" Lemma="QWM" UnicodeLemma="קום" English="to rise" Analysis="vqc" morphId="190760100012" StrongNumberX="6965" Language="H" Unicode="קוּם־‎" nodeId="190760100020010" Length="1">QW.M-</Node>
                    </Node>
                  </Node>
                  <Node Id="7.10" Cat="PP" Start="2" End="4" Rule="Pp2PP" Head="0" Language="H" nodeId="190760100030031" Length="3">
                    <Node Id="7.11" Cat="pp" Start="2" End="4" Rule="PrepNp" Head="1" Language="H" nodeId="190760100030030" Length="3">
                      <Node Id="7.12" Cat="pp" Start="2" End="2" Rule="P2PP" Head="0" Language="H" nodeId="190760100030011" Length="1">
                        <Node Id="7.13" Cat="prep" Start="2" End="2" Lemma="L:" UnicodeLemma="לְ" English="for" Analysis="Pp" morphId="190760100021" StrongNumberX="3807a" Language="H" Unicode="לַ‎" nodeId="190760100030010" Length="1">LA</Node>
                      </Node>
                      <Node Id="7.14" Cat="np" Start="3" End="4" Rule="DetNP" Head="1" Language="H" nodeId="190760100040020" Length="2">
                        <Node Id="7.15" Cat="art" Start="3" End="3" Lemma="HA" UnicodeLemma="הַ" English="the" Analysis="Pa" morphId="190760100022" StrongNumberX="1886a" Language="H" Unicode="‎" nodeId="190760100040010" Length="1">_</Node>
                        <Node Id="7.16" Cat="np" Start="4" End="4" Rule="N2NP" Head="0" Language="H" nodeId="190760100050011" Length="1">
                          <Node Id="7.17" Cat="noun" Start="4" End="4" Lemma="MI$:P.F+" UnicodeLemma="מִשְׁפָּט" English="judgment" Analysis="ncmsa" morphId="190760100023" StrongNumberX="4941" Language="H" Unicode="מִּשְׁפָּ֥ט‎" nodeId="190760100050010" Length="1">M.I$:P.F71+</Node>
                        </Node>
                      </Node>
                    </Node>
                  </Node>
                  <Node Id="7.18" Cat="S" Start="5" End="5" Rule="Np2S" Head="0" Language="H" nodeId="190760100060012" Length="1">
                    <Node Id="7.19" Cat="np" Start="5" End="5" Rule="N2NP" Head="0" Language="H" nodeId="190760100060011" Length="1">
                      <Node Id="7.20" Cat="noun" Start="5" End="5" Lemma="):ELOHIYM" UnicodeLemma="אֱלֹהִים" English="God" Analysis="ncmpa" morphId="190760100031" StrongNumberX="0430" Language="H" Unicode="אֱלֹהִ֑ים‎" nodeId="190760100060010" Length="1">):ELOHI92YM</Node>
                    </Node>
                  </Node>
                  <Node Id="7.21" Cat="PP" Start="6" End="10" Rule="Pp2PP" Head="0" Language="H" nodeId="190760100070051" Length="5">
                    <Node Id="7.22" Cat="pp" Start="6" End="10" Rule="PrepCL" Head="1" Language="H" nodeId="190760100070050" Length="5">
                      <Node Id="7.23" Cat="pp" Start="6" End="6" Rule="P2PP" Head="0" Language="H" nodeId="190760100070011" Length="1">
                        <Node Id="7.24" Cat="prep" Start="6" End="6" Lemma="L:" UnicodeLemma="לְ" English="to" Analysis="Pp" morphId="190760100041" StrongNumberX="3807a" Language="H" Unicode="לְ‎" nodeId="190760100070010" Length="1">L:</Node>
                      </Node>
                      <Node Id="7.25" Cat="CL" Start="7" End="10" Rule="V-O" Head="0" Language="H" nodeId="190760100080040" Length="4">
                        <Node Id="7.26" Cat="V" Start="7" End="7" Rule="Vp2V" Head="0" Language="H" nodeId="190760100080012" Length="1">
                          <Node Id="7.27" Cat="vp" Start="7" End="7" Rule="V2VP" Head="0" Language="H" nodeId="190760100080011" Length="1">
                            <Node Id="7.28" Cat="verb" Start="7" End="7" Lemma="Y$(" UnicodeLemma="ישׁע" English="save" Analysis="vhc" morphId="190760100042" StrongNumberX="3467" Language="H" Unicode="הוֹשִׁ֖יעַ‎" nodeId="190760100080010" Length="1">HOW$I73Y(A</Node>
                          </Node>
                        </Node>
                        <Node Id="7.29" Cat="O" Start="8" End="10" Rule="Np2O" Head="0" Language="H" nodeId="190760100090031" Length="3">
                          <Node Id="7.30" Cat="np" Start="8" End="10" Rule="QuanNP" Head="1" Language="H" nodeId="190760100090030" Length="3">
                            <Node Id="7.31" Cat="np" Start="8" End="8" Rule="N2NP" Head="0" Language="H" nodeId="190760100090011" Length="1">
                              <Node Id="7.32" Cat="noun" Start="8" End="8" Lemma="K.OL" UnicodeLemma="כֹּל" English="all of" Analysis="ncmsc" morphId="190760100051" StrongNumberX="3605" Language="H" Unicode="כָּל־‎" nodeId="190760100090010" Length="1">K.FL-</Node>
                            </Node>
                            <Node Id="7.33" Cat="np" Start="9" End="10" Rule="NPofNP" Head="0" Language="H" nodeId="190760100100020" Length="2">
                              <Node Id="7.34" Cat="np" Start="9" End="9" Rule="Adj2NP" Head="0" Language="H" nodeId="190760100100012" Length="1">
                                <Node Id="7.35" Cat="adjp" Start="9" End="9" Rule="Adj2Adjp" Head="0" Language="H" nodeId="190760100100011" Length="1">
                                  <Node Id="7.36" Cat="adj" Start="9" End="9" Lemma="(FNFW" UnicodeLemma="עָנָו" English="afflicted ones of" Analysis="ampc" morphId="190760100061" StrongNumberX="6035" Language="H" Unicode="עַנְוֵי־‎" nodeId="190760100100010" Length="1">(AN:W"Y-</Node>
                                </Node>
                              </Node>
                              <Node Id="7.37" Cat="np" Start="10" End="10" Rule="N2NP" Head="0" Language="H" nodeId="190760100110011" Length="1">
                                <Node Id="7.38" Cat="noun" Start="10" End="10" Lemma=")EREC" UnicodeLemma="אֶרֶץ" English="land" Analysis="ncfsa" morphId="190760100071" StrongNumberX="0776" Language="H" Unicode="אֶ֣רֶץ‎" nodeId="190760100110010" Length="1">)E74REC</Node>
                              </Node>
                            </Node>
                          </Node>
                        </Node>
                      </Node>
                    </Node>
                  </Node>
                </Node>
              </Node>
            </Node>
          </Node>
          <Node Id="50.1" Cat="CL" Start="11" End="11" Rule="Intj2CL" Head="0" Language="H" nodeId="190760100120012" Length="1">
            <Node Id="50.2" Cat="ijp" Start="11" End="11" Rule="Ij2Ijp" Head="0" Language="H" nodeId="190760100120011" Length="1">
              <Node Id="50.3" Cat="ij" Start="11" End="11" Lemma="SELFH" UnicodeLemma="סֶלָה" English="selah" Analysis="Pi" morphId="190760100081" StrongNumberX="5542" Language="H" Unicode="׃‎סֶֽלָה‎" nodeId="190760100120010" Length="1">SE75LFH00</Node>
            </Node>
          </Node>
        </Node>
      </Tree>
    </Trees>
  </Sentence>
  <Sentence ID="ps76:11">
    <Trees>
      <Tree>
        <Node Cat="S" Head="0" Start="0" End="7" nodeId="190760110010080" Length="8">
          <Node Id="1.1" Cat="cjp" Start="0" End="0" Rule="Cj2Cjp" Head="0" Language="H" nodeId="190760110010011" Length="1">
            <Node Id="1.2" Cat="cj" Start="0" End="0" Lemma="K.IY_2" UnicodeLemma="כִּי_2" English="surely" Analysis="Pc" morphId="190760110011" StrongNumberX="3588" Language="H" Unicode="כִּֽי־‎" nodeId="190760110010010" Length="1">K.I75Y-</Node>
          </Node>
          <Node Id="2.1" Cat="CL" Start="1" End="4" Rule="S-V-O" Head="1" Language="H" nodeId="190760110020040" Length="4">
            <Node Id="2.2" Cat="S" Start="1" End="2" Rule="Np2S" Head="0" Language="H" nodeId="190760110020021" Length="2">
              <Node Id="2.3" Cat="np" Start="1" End="2" Rule="NPofNP" Head="0" Language="H" nodeId="190760110020020" Length="2">
                <Node Id="2.4" Cat="np" Start="1" End="1" Rule="N2NP" Head="0" Language="H" nodeId="190760110020011" Length="1">
                  <Node Id="2.5" Cat="noun" Start="1" End="1" Lemma="X&quot;MFH" UnicodeLemma="חֵמָה" English="wrath of" Analysis="ncfsc" morphId="190760110021" StrongNumberX="2534" Language="H" Unicode="חֲמַ֣ת‎" nodeId="190760110020010" Length="1">X:AMA74T</Node>
                </Node>
                <Node Id="2.6" Cat="np" Start="2" End="2" Rule="N2NP" Head="0" Language="H" nodeId="190760110030011" Length="1">
                  <Node Id="2.7" Cat="noun" Start="2" End="2" Lemma=")FDFM_1" UnicodeLemma="אָדָם_1" English="man" Analysis="ncmsa" morphId="190760110031" StrongNumberX="0120" Language="H" Unicode="אָדָ֣ם‎" nodeId="190760110030010" Length="1">)FDF74M</Node>
                </Node>
              </Node>
            </Node>
            <Node Id="2.8" Cat="V" Start="3" End="3" Rule="Vp2V" Head="0" Language="H" nodeId="190760110040012" Length="1">
              <Node Id="2.9" Cat="vp" Start="3" End="3" Rule="V2VP" Head="0" Language="H" nodeId="190760110040011" Length="1">
                <Node Id="2.10" Cat="verb" Start="3" End="3" Lemma="YDH_2" UnicodeLemma="ידה_2" English="she praises" Analysis="vhi3fs" morphId="190760110041" StrongNumberX="3034" Language="H" Unicode="תּוֹד‎" nodeId="190760110040010" Length="1">T.OWD</Node>
              </Node>
            </Node>
            <Node Id="2.11" Cat="O" Start="4" End="4" Rule="Np2O" Head="0" Language="H" nodeId="190760110050012" Length="1">
              <Node Id="2.12" Cat="np" Start="4" End="4" Rule="Pron2NP" Head="0" Language="H" nodeId="190760110050011" Length="1">
                <Node Id="2.13" Cat="pron" Start="4" End="4" Lemma=":KF" UnicodeLemma="ְכָ" English="you" Analysis="psv2msXe" morphId="190760110042" StrongNumberX="3509b" Language="H" Unicode="ֶ֑ךָּ‎" nodeId="190760110050010" Length="1">E92K.F</Node>
              </Node>
            </Node>
          </Node>
          <Node Id="10.1" Cat="CL" Start="5" End="7" Rule="O-V" Head="1" Language="H" nodeId="190760110060030" Length="3">
            <Node Id="10.2" Cat="O" Start="5" End="6" Rule="Np2O" Head="0" Language="H" nodeId="190760110060021" Length="2">
              <Node Id="10.3" Cat="np" Start="5" End="6" Rule="NPofNP" Head="0" Language="H" nodeId="190760110060020" Length="2">
                <Node Id="10.4" Cat="np" Start="5" End="5" Rule="N2NP" Head="0" Language="H" nodeId="190760110060011" Length="1">
                  <Node Id="10.5" Cat="noun" Start="5" End="5" Lemma="$:)&quot;RIYT" UnicodeLemma="שְׁאֵרִית" English="survivor of" Analysis="ncfsc" morphId="190760110051" StrongNumberX="7611" Language="H" Unicode="שְׁאֵרִ֖ית‎" nodeId="190760110060010" Length="1">$:)"RI73YT</Node>
                </Node>
                <Node Id="10.6" Cat="np" Start="6" End="6" Rule="N2NP" Head="0" Language="H" nodeId="190760110070011" Length="1">
                  <Node Id="10.7" Cat="noun" Start="6" End="6" Lemma="X&quot;MFH" UnicodeLemma="חֵמָה" English="wraths" Analysis="ncfpa" morphId="190760110061" StrongNumberX="2534" Language="H" Unicode="חֵמֹ֣ת‎" nodeId="190760110070010" Length="1">X"MO74T</Node>
                </Node>
              </Node>
            </Node>
            <Node Id="10.8" Cat="V" Start="7" End="7" Rule="Vp2V" Head="0" Language="H" nodeId="190760110080012" Length="1">
              <Node Id="10.9" Cat="vp" Start="7" End="7" Rule="V2VP" Head="0" Language="H" nodeId="190760110080011" Length="1">
                <Node Id="10.10" Cat="verb" Start="7" End="7" Lemma="XGR" UnicodeLemma="חגר" English="you restrain" Analysis="vqi2ms" morphId="190760110071" StrongNumberX="2296" Language="H" Unicode="׃‎תַּחְגֹּֽר‎" nodeId="190760110080010" Length="1">T.AX:G.O75R00</Node>
              </Node>
            </Node>
          </Node>
        </Node>
      </Tree>
    </Trees>
  </Sentence>
  <Sentence ID="ps76:12">
    <Trees>
      <Tree>
        <Node Cat="S" Head="0" Start="0" End="14" nodeId="190760120010150" Length="15">
          <Node Id="1.1" Cat="CL" Start="0" End="0" Rule="V2CL" Head="0" Language="H" nodeId="190760120010013" Length="1">
            <Node Id="1.2" Cat="V" Start="0" End="0" Rule="Vp2V" Head="0" Language="H" nodeId="190760120010012" Length="1">
              <Node Id="1.3" Cat="vp" Start="0" End="0" Rule="V2VP" Head="0" Language="H" nodeId="190760120010011" Length="1">
                <Node Id="1.4" Cat="verb" Start="0" End="0" Lemma="NDR" UnicodeLemma="נדר" English="make vows!" Analysis="vqvmp" morphId="190760120011" StrongNumberX="5087" Language="H" Unicode="נִֽדֲר֣וּ‎" nodeId="190760120010010" Length="1">NI75D:AR74W.</Node>
              </Node>
            </Node>
          </Node>
          <Node Id="2.1" Cat="cjp" Start="1" End="1" Rule="Cj2Cjp" Head="0" Language="H" nodeId="190760120020011" Length="1">
            <Node Id="2.2" Cat="cj" Start="1" End="1" Lemma="W:" UnicodeLemma="וְ" English="and" Analysis="Pc" morphId="190760120021" StrongNumberX="2050b" Language="H" Unicode="וְ‎" nodeId="190760120020010" Length="1">W:</Node>
          </Node>
          <Node Id="4.1" Cat="CL" Start="2" End="6" Rule="V-PP" Head="0" Language="H" nodeId="190760120030050" Length="5">
            <Node Id="4.2" Cat="V" Start="2" End="2" Rule="Vp2V" Head="0" Language="H" nodeId="190760120030012" Length="1">
              <Node Id="4.3" Cat="vp" Start="2" End="2" Rule="V2VP" Head="0" Language="H" nodeId="190760120030011" Length="1">
                <Node Id="4.4" Cat="verb" Start="2" End="2" Lemma="$LM" UnicodeLemma="שׁלם" English="fulfill!" Analysis="vpvmp" morphId="190760120022" StrongNumberX="7999" Language="H" Unicode="שַׁלְּמוּ֮‎" nodeId="190760120030010" Length="1">$AL.:MW.02</Node>
              </Node>
            </Node>
            <Node Id="4.5" Cat="PP" Start="3" End="6" Rule="Pp2PP" Head="0" Language="H" nodeId="190760120040041" Length="4">
              <Node Id="4.6" Cat="pp" Start="3" End="6" Rule="PrepNp" Head="1" Language="H" nodeId="190760120040040" Length="4">
                <Node Id="4.7" Cat="pp" Start="3" End="3" Rule="P2PP" Head="0" Language="H" nodeId="190760120040011" Length="1">
                  <Node Id="4.8" Cat="prep" Start="3" End="3" Lemma="L:" UnicodeLemma="לְ" English="to" Analysis="Pp" morphId="190760120031" StrongNumberX="3807a" Language="H" Unicode="לַ‎" nodeId="190760120040010" Length="1">LA</Node>
                </Node>
                <Node Id="4.9" Cat="np" Start="4" End="6" Rule="Np-Appos" Head="0" Language="H" nodeId="190760120050030" Length="3">
                  <Node Id="4.10" Cat="np" Start="4" End="4" Rule="N2NP" Head="0" Language="H" nodeId="190760120050011" Length="1">
                    <Node Id="4.11" Cat="noun" Start="4" End="4" Lemma="YHWH" UnicodeLemma="יהוה" English="Yahweh" Analysis="np" morphId="190760120032" StrongNumberX="3068" Language="H" Unicode="יהוָ֪ה‎" nodeId="190760120050010" Length="1">YHWF93H</Node>
                  </Node>
                  <Node Id="4.12" Cat="np" Start="5" End="6" Rule="NPofNP" Head="0" Language="H" nodeId="190760120060020" Length="2">
                    <Node Id="4.13" Cat="np" Start="5" End="5" Rule="N2NP" Head="0" Language="H" nodeId="190760120060011" Length="1">
                      <Node Id="4.14" Cat="noun" Start="5" End="5" Lemma="):ELOHIYM" UnicodeLemma="אֱלֹהִים" English="God of" Analysis="ncmpc" morphId="190760120041" StrongNumberX="0430" Language="H" Unicode="אֱ‍ֽלֹהֵ֫י‎" nodeId="190760120060010" Length="1">):E35LOH"60Y</Node>
                    </Node>
                    <Node Id="4.15" Cat="np" Start="6" End="6" Rule="Pron2NP" Head="0" Language="H" nodeId="190760120070011" Length="1">
                      <Node Id="4.16" Cat="pron" Start="6" End="6" Lemma=":KEM" UnicodeLemma="ְכֶם" English="you" Analysis="psn2mp" morphId="190760120042" StrongNumberX="3641b" Language="H" Unicode="כֶ֥ם‎" nodeId="190760120070010" Length="1">KE71M</Node>
                    </Node>
                  </Node>
                </Node>
              </Node>
            </Node>
          </Node>
          <Node Id="17.1" Cat="CL" Start="7" End="14" Rule="S-V-O-PP" Head="1" Language="H" nodeId="190760120080080" Length="8">
            <Node Id="17.2" Cat="S" Start="7" End="9" Rule="Np2S" Head="0" Language="H" nodeId="190760120080031" Length="3">
              <Node Id="17.3" Cat="np" Start="7" End="9" Rule="QuanNP" Head="1" Language="H" nodeId="190760120080030" Length="3">
                <Node Id="17.4" Cat="np" Start="7" End="7" Rule="N2NP" Head="0" Language="H" nodeId="190760120080011" Length="1">
                  <Node Id="17.5" Cat="noun" Start="7" End="7" Lemma="K.OL" UnicodeLemma="כֹּל" English="all of" Analysis="ncmsc" morphId="190760120051" StrongNumberX="3605" Language="H" Unicode="כָּל־‎" nodeId="190760120080010" Length="1">K.FL-</Node>
                </Node>
                <Node Id="17.6" Cat="np" Start="8" End="9" Rule="NPofNP" Head="0" Language="H" nodeId="190760120090020" Length="2">
                  <Node Id="17.7" Cat="np" Start="8" End="8" Rule="advp2np" Head="0" Language="H" nodeId="190760120090012" Length="1">
                    <Node Id="17.8" Cat="advp" Start="8" End="8" Rule="Adv2Advp" Head="0" Language="H" nodeId="190760120090011" Length="1">
                      <Node Id="17.9" Cat="adv" Start="8" End="8" Lemma="SFBIYB" UnicodeLemma="סָבִיב" English="neighbors of" Analysis="Pd" morphId="190760120061" StrongNumberX="5439" Language="H" Unicode="סְבִיבָ֑י‎" nodeId="190760120090010" Length="1">S:BIYBF92Y</Node>
                    </Node>
                  </Node>
                  <Node Id="17.10" Cat="np" Start="9" End="9" Rule="Pron2NP" Head="0" Language="H" nodeId="190760120100011" Length="1">
                    <Node Id="17.11" Cat="pron" Start="9" End="9" Lemma="OW" UnicodeLemma="וֹ" English="him" Analysis="psn3ms" morphId="190760120062" StrongNumberX="2050c" Language="H" Unicode="ו‎" nodeId="190760120100010" Length="1">W</Node>
                  </Node>
                </Node>
              </Node>
            </Node>
            <Node Id="17.12" Cat="V" Start="10" End="10" Rule="Vp2V" Head="0" Language="H" nodeId="190760120110012" Length="1">
              <Node Id="17.13" Cat="vp" Start="10" End="10" Rule="V2VP" Head="0" Language="H" nodeId="190760120110011" Length="1">
                <Node Id="17.14" Cat="verb" Start="10" End="10" Lemma="YBL" UnicodeLemma="יבל" English="let him bring" Analysis="vhi3mp{1}Jm" morphId="190760120071" StrongNumberX="2986" Language="H" Unicode="יוֹבִ֥ילוּ‎" nodeId="190760120110010" Length="1">YOWBI71YLW.</Node>
              </Node>
            </Node>
            <Node Id="17.15" Cat="O" Start="11" End="11" Rule="Np2O" Head="0" Language="H" nodeId="190760120120012" Length="1">
              <Node Id="17.16" Cat="np" Start="11" End="11" Rule="N2NP" Head="0" Language="H" nodeId="190760120120011" Length="1">
                <Node Id="17.17" Cat="noun" Start="11" End="11" Lemma="$AY" UnicodeLemma="שַׁי" English="gift" Analysis="ncmsa" morphId="190760120081" StrongNumberX="7862" Language="H" Unicode="שַׁ֝֗י‎" nodeId="190760120120010" Length="1">11$A81Y</Node>
              </Node>
            </Node>
            <Node Id="17.18" Cat="PP" Start="12" End="14" Rule="Pp2PP" Head="0" Language="H" nodeId="190760120130031" Length="3">
              <Node Id="17.19" Cat="pp" Start="12" End="14" Rule="PrepNp" Head="1" Language="H" nodeId="190760120130030" Length="3">
                <Node Id="17.20" Cat="pp" Start="12" End="12" Rule="P2PP" Head="0" Language="H" nodeId="190760120130011" Length="1">
                  <Node Id="17.21" Cat="prep" Start="12" End="12" Lemma="L:" UnicodeLemma="לְ" English="to" Analysis="Pp" morphId="190760120091" StrongNumberX="3807a" Language="H" Unicode="לַ‎" nodeId="190760120130010" Length="1">LA</Node>
                </Node>
                <Node Id="17.22" Cat="np" Start="13" End="14" Rule="DetNP" Head="1" Language="H" nodeId="190760120140020" Length="2">
                  <Node Id="17.23" Cat="art" Start="13" End="13" Lemma="HA" UnicodeLemma="הַ" English="the" Analysis="Pa" morphId="190760120092" StrongNumberX="1886a" Language="H" Unicode="‎" nodeId="190760120140010" Length="1">_</Node>
                  <Node Id="17.24" Cat="np" Start="14" End="14" Rule="N2NP" Head="0" Language="H" nodeId="190760120150011" Length="1">
                    <Node Id="17.25" Cat="noun" Start="14" End="14" Lemma="MOWRF)" UnicodeLemma="מוֹרָא" English="One being feared" Analysis="ncmsa" morphId="190760120093" StrongNumberX="4172" Language="H" Unicode="׃‎מּוֹרָֽא‎" nodeId="190760120150010" Length="1">M.OWRF75)00</Node>
                  </Node>
                </Node>
              </Node>
            </Node>
          </Node>
        </Node>
      </Tree>
    </Trees>
  </Sentence>
  <Sentence ID="ps76:13">
    <Trees>
      <Tree>
        <Node Cat="S" Head="0" Start="0" End="6" nodeId="190760130010070" Length="7">
          <Node Id="2.1" Cat="CL" Start="0" End="2" Rule="V-O" Head="0" Language="H" nodeId="190760130010030" Length="3">
            <Node Id="2.2" Cat="V" Start="0" End="0" Rule="Vp2V" Head="0" Language="H" nodeId="190760130010012" Length="1">
              <Node Id="2.3" Cat="vp" Start="0" End="0" Rule="V2VP" Head="0" Language="H" nodeId="190760130010011" Length="1">
                <Node Id="2.4" Cat="verb" Start="0" End="0" Lemma="BCR_2" UnicodeLemma="בצר_2" English="he breaks" Analysis="vqi3ms" morphId="190760130011" StrongNumberX="1219a" Language="H" Unicode="יִ֭בְצֹר‎" nodeId="190760130010010" Length="1">13YIB:COR</Node>
              </Node>
            </Node>
            <Node Id="2.5" Cat="O" Start="1" End="2" Rule="Np2O" Head="0" Language="H" nodeId="190760130020021" Length="2">
              <Node Id="2.6" Cat="np" Start="1" End="2" Rule="NPofNP" Head="0" Language="H" nodeId="190760130020020" Length="2">
                <Node Id="2.7" Cat="np" Start="1" End="1" Rule="N2NP" Head="0" Language="H" nodeId="190760130020011" Length="1">
                  <Node Id="2.8" Cat="noun" Start="1" End="1" Lemma="RW.XA" UnicodeLemma="רוּחַ" English="spirit of" Analysis="ncfsc" morphId="190760130021" StrongNumberX="7307" Language="H" Unicode="ר֣וּחַ‎" nodeId="190760130020010" Length="1">R74W.XA</Node>
                </Node>
                <Node Id="2.9" Cat="np" Start="2" End="2" Rule="N2NP" Head="0" Language="H" nodeId="190760130030011" Length="1">
                  <Node Id="2.10" Cat="noun" Start="2" End="2" Lemma="NFGIYD" UnicodeLemma="נָגִיד" English="rulers" Analysis="ncmpa" morphId="190760130031" StrongNumberX="5057" Language="H" Unicode="נְגִידִ֑ים‎" nodeId="190760130030010" Length="1">N:GIYDI92YM</Node>
                </Node>
              </Node>
            </Node>
          </Node>
          <Node Id="7.1" Cat="CL" Start="3" End="6" Rule="V-PP" Head="0" Language="H" nodeId="190760130040040" Length="4">
            <Node Id="7.2" Cat="V" Start="3" End="3" Rule="Vp2V" Head="0" Language="H" nodeId="190760130040012" Length="1">
              <Node Id="7.3" Cat="vp" Start="3" End="3" Rule="V2VP" Head="0" Language="H" nodeId="190760130040011" Length="1">
                <Node Id="7.4" Cat="verb" Start="3" End="3" Lemma="YR)_1" UnicodeLemma="ירא_1" English="one being feared" Analysis="vnPmsa" morphId="190760130041" StrongNumberX="3372" Language="H" Unicode="נ֝וֹרָ֗א‎" nodeId="190760130040010" Length="1">11NOWRF81)</Node>
              </Node>
            </Node>
            <Node Id="7.5" Cat="PP" Start="4" End="6" Rule="Pp2PP" Head="0" Language="H" nodeId="190760130050031" Length="3">
              <Node Id="7.6" Cat="pp" Start="4" End="6" Rule="PrepNp" Head="1" Language="H" nodeId="190760130050030" Length="3">
                <Node Id="7.7" Cat="pp" Start="4" End="4" Rule="P2PP" Head="0" Language="H" nodeId="190760130050011" Length="1">
                  <Node Id="7.8" Cat="prep" Start="4" End="4" Lemma="L:" UnicodeLemma="לְ" English="by" Analysis="Pp" morphId="190760130051" StrongNumberX="3807a" Language="H" Unicode="לְ‎" nodeId="190760130050010" Length="1">L:</Node>
                </Node>
                <Node Id="7.9" Cat="np" Start="5" End="6" Rule="NPofNP" Head="0" Language="H" nodeId="190760130060020" Length="2">
                  <Node Id="7.10" Cat="np" Start="5" End="5" Rule="N2NP" Head="0" Language="H" nodeId="190760130060011" Length="1">
                    <Node Id="7.11" Cat="noun" Start="5" End="5" Lemma="MELEK:_1" UnicodeLemma="מֶלֶךְ_1" English="kings of" Analysis="ncmpc" morphId="190760130052" StrongNumberX="4428" Language="H" Unicode="מַלְכֵי־‎" nodeId="190760130060010" Length="1">MAL:K"Y-</Node>
                  </Node>
                  <Node Id="7.12" Cat="np" Start="6" End="6" Rule="N2NP" Head="0" Language="H" nodeId="190760130070011" Length="1">
                    <Node Id="7.13" Cat="noun" Start="6" End="6" Lemma=")EREC" UnicodeLemma="אֶרֶץ" English="earth" Analysis="ncfsa" morphId="190760130061" StrongNumberX="0776" Language="H" Unicode="׃‎אָֽרֶץ‎" nodeId="190760130070010" Length="1">)F75REC00</Node>
                  </Node>
                </Node>
              </Node>
            </Node>
          </Node>
        </Node>
      </Tree>
    </Trees>
  </Sentence>
</Sentences>